kodo/plugins/cover_test_context.py
kodo_plugins_cover_test_context-0.1.dist-info/WHEEL
kodo_plugins_cover_test_context-0.1.dist-info/METADATA
kodo_plugins_cover_test_context-0.1.dist-info/RECORD
