Metadata-Version: 2.1
Name: kodo.plugins.cover-test-context
Version: 0.1
Summary: A Coverage.py plugin module for adding test names as contexts
Author-email: Dom Sekotill <dom.sekotill@kodo.org.uk>
Requires-Python: ~=3.9
Classifier: Development Status :: 1 - Planning
Classifier: Intended Audience :: Developers
Classifier: License :: OSI Approved :: Mozilla Public License 2.0 (MPL 2.0)
Classifier: Programming Language :: Python :: 3 :: Only
Classifier: Topic :: Software Development :: Quality Assurance
Requires-Dist: coverage >=5.0
Project-URL: Issues, https://code.kodo.org.uk/dom/cover-plugin-test-context/-/issues
Project-URL: Repository, https://code.kodo.org.uk/dom/cover-plugin-test-context
